aimlflow/VERSION
aimlflow/__init__.py
aimlflow/cli.py
aimlflow/utils.py
aimlflow/watcher.py
aim_mlflow-0.2.1.dist-info/LICENSE
aim_mlflow-0.2.1.dist-info/METADATA
aim_mlflow-0.2.1.dist-info/WHEEL
aim_mlflow-0.2.1.dist-info/entry_points.txt
aim_mlflow-0.2.1.dist-info/top_level.txt
aim_mlflow-0.2.1.dist-info/RECORD
